thousandeyes_sdk/dashboards/__init__.py
thousandeyes_sdk/dashboards/py.typed
thousandeyes_sdk/dashboards/api/__init__.py
thousandeyes_sdk/dashboards/api/dashboard_snapshots_api.py
thousandeyes_sdk/dashboards/api/dashboards_api.py
thousandeyes_sdk/dashboards/api/dashboards_filters_api.py
thousandeyes_sdk/dashboards/models/__init__.py
thousandeyes_sdk/dashboards/models/active_within.py
thousandeyes_sdk/dashboards/models/agent_status_datasource.py
thousandeyes_sdk/dashboards/models/alert_list_alert_type.py
thousandeyes_sdk/dashboards/models/alert_list_datasource.py
thousandeyes_sdk/dashboards/models/api_agent_location.py
thousandeyes_sdk/dashboards/models/api_agent_status_agent.py
thousandeyes_sdk/dashboards/models/api_agent_status_ip_info.py
thousandeyes_sdk/dashboards/models/api_agent_status_summary.py
thousandeyes_sdk/dashboards/models/api_agent_status_widget.py
thousandeyes_sdk/dashboards/models/api_agent_widget_show.py
thousandeyes_sdk/dashboards/models/api_agent_widget_type.py
thousandeyes_sdk/dashboards/models/api_aggregate_property.py
thousandeyes_sdk/dashboards/models/api_alert_list_alert.py
thousandeyes_sdk/dashboards/models/api_alert_list_widget.py
thousandeyes_sdk/dashboards/models/api_box_and_whiskers_widget.py
thousandeyes_sdk/dashboards/models/api_color_grid_widget.py
thousandeyes_sdk/dashboards/models/api_context_filter_request.py
thousandeyes_sdk/dashboards/models/api_context_filter_response.py
thousandeyes_sdk/dashboards/models/api_context_filters_response.py
thousandeyes_sdk/dashboards/models/api_dashboard.py
thousandeyes_sdk/dashboards/models/api_dashboard_asw.py
thousandeyes_sdk/dashboards/models/api_dashboard_filter_user_details.py
thousandeyes_sdk/dashboards/models/api_dashboard_snapshot.py
thousandeyes_sdk/dashboards/models/api_data_point_group.py
thousandeyes_sdk/dashboards/models/api_data_source_filter.py
thousandeyes_sdk/dashboards/models/api_data_source_filters.py
thousandeyes_sdk/dashboards/models/api_default_timespan.py
thousandeyes_sdk_dashboards-2.23.0.dist-info/licenses/LICENSE
thousandeyes_sdk_dashboards-2.23.0.dist-info/licenses/NOTICE
thousandeyes_sdk_dashboards-2.23.0.dist-info/METADATA
thousandeyes_sdk_dashboards-2.23.0.dist-info/WHEEL
thousandeyes_sdk_dashboards-2.23.0.dist-info/top_level.txt
thousandeyes_sdk_dashboards-2.23.0.dist-info/RECORD
